hive/langchain/__init__.py
hive/langchain/__version__.py
hive/langchain/chat_models.py
hive/langchain/ollama.py
hive/langchain/py.typed
hive_langchain-0.1.0.dist-info/METADATA
hive_langchain-0.1.0.dist-info/WHEEL
hive_langchain-0.1.0.dist-info/top_level.txt
hive_langchain-0.1.0.dist-info/RECORD
